trackbert/__init__.py
trackbert/__main__.py
trackbert/alembic.ini
trackbert/config.dist.ini
trackbert/assets/parcel-delivery-icon.txt
trackbert/assets/parcel-delivery-icon.webp
trackbert/classes/__init__.py
trackbert/classes/database.py
trackbert/classes/http.py
trackbert/classes/tracker.py
trackbert/migrations/env.py
trackbert/migrations/script.py.mako
trackbert/migrations/versions/770fdbef1f4e_initial_migration.py
trackbert/migrations/versions/91ca1665ca83_shipment_disabled.py
trackbert/trackers/__init__.py
trackbert/trackers/base.py
trackbert/trackers/dhl.py
trackbert/trackers/dpd.py
trackbert/trackers/fedex.py
trackbert/trackers/gls.py
trackbert/trackers/keydelivery.py
trackbert/trackers/postat.py
trackbert-0.2.6.dist-info/METADATA
trackbert-0.2.6.dist-info/WHEEL
trackbert-0.2.6.dist-info/entry_points.txt
trackbert-0.2.6.dist-info/licenses/LICENSE
trackbert-0.2.6.dist-info/RECORD
