Metadata-Version: 2.1
Name: trackbert
Version: 0.2.6
Summary: Python application tracking your shipments
Project-URL: Homepage, https://kumig.it/kumitterer/trackbert
Project-URL: Bug Tracker, https://kumig.it/kumitterer/trackbert/issues
Author-email: Kumi Mitterer <trackbert@kumi.email>
License: Copyright (c) 2023 Kumi Mitterer <trackbert@kumi.email>
License-File: LICENSE
Classifier: License :: OSI Approved :: MIT License
Classifier: Operating System :: OS Independent
Classifier: Programming Language :: Python :: 3
Requires-Python: >=3.10
Requires-Dist: alembic
Requires-Dist: dhltrack
Requires-Dist: dpdtrack
Requires-Dist: fedextrack
Requires-Dist: glsapi
Requires-Dist: postat
Requires-Dist: pykeydelivery>=0.9.1
Requires-Dist: python-dateutil
Requires-Dist: sqlalchemy
Requires-Dist: tabulate
